kernelforge/_kernelforge.cpython-313-darwin.so
kernelforge/__init__.py
kernelforge/.dylibs/libgfortran.5.dylib
kernelforge/.dylibs/libquadmath.0.dylib
kernelforge/.dylibs/libgcc_s.1.1.dylib
kernelforge/.dylibs/libgomp.1.dylib
kernelforge-0.1.8.dist-info/RECORD
kernelforge-0.1.8.dist-info/WHEEL
kernelforge-0.1.8.dist-info/METADATA
kernelforge-0.1.8.dist-info/licenses/LICENSE
