Metadata-Version: 2.2
Name: kernelforge
Version: 0.1.8
Summary: Optimzed Kernels for ML
Author: Anders Christensen
License: MIT
Project-URL: Homepage, https://github.com/youruser/kernelforge
Project-URL: Issues, https://github.com/youruser/kernelforge/issues
Requires-Python: >=3.10
Requires-Dist: numpy>=2.00
Provides-Extra: test
Requires-Dist: pytest>=8; extra == "test"
Requires-Dist: pytest-xdist; extra == "test"
Requires-Dist: pytest-cov; extra == "test"
Requires-Dist: pytest-timeout; extra == "test"
